practicer/__init__.py
practicer/main.py
practicer-0.1.0.dist-info/METADATA
practicer-0.1.0.dist-info/WHEEL
practicer-0.1.0.dist-info/RECORD
