Metadata-Version: 2.3
Name: practicer
Version: 0.1.0
Summary: 
Author: Your Name
Author-email: you@example.com
Requires-Python: >=3.13
Classifier: Programming Language :: Python :: 3
Classifier: Programming Language :: Python :: 3.13
Requires-Dist: fastapi (>=0.115.8,<0.116.0)
Requires-Dist: uvicorn (>=0.34.0,<0.35.0)
